terminal_search/__init__.py
terminal_search/__main__.py
terminal_search/app.py
terminal_search/main.tcss
terminal_search/search.py
terminal_search-0.1.1.dist-info/METADATA
terminal_search-0.1.1.dist-info/WHEEL
terminal_search-0.1.1.dist-info/entry_points.txt
terminal_search-0.1.1.dist-info/RECORD
