Metadata-Version: 2.4
Name: terminal-search
Version: 0.1.1
Summary: AI-powered search, right in your terminal
Project-URL: Homepage, https://textual-web.io/craig/terminal-search
Project-URL: Repository, https://github.com/CragglesG/terminal-search
Author-email: Craig Giles <me@craigg.dev>
License-Expression: MIT
Requires-Dist: exa-py
Requires-Dist: python-dotenv
Requires-Dist: textual
